tricycle/__init__.py
tricycle/_meta.py
tricycle/_multi_cancel.py
tricycle/_rwlock.py
tricycle/_service_nursery.py
tricycle/_streams.py
tricycle/_tree_var.py
tricycle/_version.py
tricycle/py.typed
tricycle/_tests/__init__.py
tricycle/_tests/conftest.py
tricycle/_tests/test_meta.py
tricycle/_tests/test_multi_cancel.py
tricycle/_tests/test_rwlock.py
tricycle/_tests/test_service_nursery.py
tricycle/_tests/test_streams.py
tricycle/_tests/test_tree_var.py
tricycle-0.4.1.dist-info/LICENSE
tricycle-0.4.1.dist-info/LICENSE.APACHE2
tricycle-0.4.1.dist-info/LICENSE.MIT
tricycle-0.4.1.dist-info/METADATA
tricycle-0.4.1.dist-info/WHEEL
tricycle-0.4.1.dist-info/top_level.txt
tricycle-0.4.1.dist-info/RECORD
