Metadata-Version: 2.1
Name: tricycle
Version: 0.4.1
Summary: Miscellaneous extensions for Trio, the friendly async I/O library
Home-page: https://github.com/oremanj/tricycle
Author: Joshua Oreman
Author-email: oremanj@gmail.com
License: MIT -or- Apache License 2.0
Keywords: async,trio
Classifier: License :: OSI Approved :: MIT License
Classifier: License :: OSI Approved :: Apache Software License
Classifier: Framework :: Trio
Classifier: Operating System :: POSIX :: Linux
Classifier: Operating System :: MacOS :: MacOS X
Classifier: Programming Language :: Python :: 3 :: Only
Classifier: Programming Language :: Python :: Implementation :: CPython
Classifier: Development Status :: 3 - Alpha
Classifier: Intended Audience :: Developers
Requires-Python: >=3.8
License-File: LICENSE
License-File: LICENSE.APACHE2
License-File: LICENSE.MIT
Requires-Dist: trio >=0.23.0
